component/__init__.py
component/definition.py
component/expression.py
component/identifier.py
component/option.py
component/reference.py
component/specification.py
statement/__init__.py
statement/alter.py
statement/create.py
statement/delete.py
statement/drop.py
statement/explain.py
statement/insert.py
statement/rename.py
statement/replace.py
statement/select.py
statement/set.py
statement/show.py
statement/truncate.py
statement/update.py
statement/use.py
mysqlparser-1.0.0.dist-info/LICENSE
mysqlparser-1.0.0.dist-info/METADATA
mysqlparser-1.0.0.dist-info/WHEEL
mysqlparser-1.0.0.dist-info/top_level.txt
mysqlparser-1.0.0.dist-info/RECORD
