Metadata-Version: 2.1
Name: mysqlparser
Version: 1.0.0
Summary: SQL parser
Home-page: UNKNOWN
License: UNKNOWN
Platform: UNKNOWN
License-File: LICENSE
